wagtail_photo_gallery/__init__.py
wagtail_photo_gallery/blocks.py
wagtail_photo_gallery/forms.py
wagtail_photo_gallery/mixins.py
wagtail_photo_gallery/models.py
wagtail_photo_gallery/panels.py
wagtail_photo_gallery/utils.py
wagtail_photo_gallery/views.py
wagtail_photo_gallery/wagtail_hooks.py
wagtail_photo_gallery/widgets.py
wagtail_photo_gallery/locale/de/LC_MESSAGES/django.po
wagtail_photo_gallery/migrations/0001_initial.py
wagtail_photo_gallery/migrations/0002_alter_album_options.py
wagtail_photo_gallery/migrations/0003_alter_album_collection.py
wagtail_photo_gallery/migrations/0004_album_date_album_place.py
wagtail_photo_gallery/migrations/0005_alter_album_slug.py
wagtail_photo_gallery/migrations/0006_alter_album_description.py
wagtail_photo_gallery/migrations/0007_alter_albumimage_image_alter_albumimage_thumb.py
wagtail_photo_gallery/migrations/__init__.py
wagtail_photo_gallery/migrations/__pycache__/0001_initial.cpython-312.pyc
wagtail_photo_gallery/migrations/__pycache__/0002_alter_album_options.cpython-312.pyc
wagtail_photo_gallery/migrations/__pycache__/0003_alter_album_collection.cpython-312.pyc
wagtail_photo_gallery/migrations/__pycache__/0004_album_date_album_place.cpython-312.pyc
wagtail_photo_gallery/migrations/__pycache__/0005_alter_album_slug.cpython-312.pyc
wagtail_photo_gallery/migrations/__pycache__/0006_alter_album_description.cpython-312.pyc
wagtail_photo_gallery/migrations/__pycache__/0007_alter_albumimage_image_alter_albumimage_thumb.cpython-312.pyc
wagtail_photo_gallery/migrations/__pycache__/__init__.cpython-312.pyc
wagtail_photo_gallery/static/app.js
wagtail_photo_gallery/static/photo_gallery.css
wagtail_photo_gallery/static/photo_gallery_admin.css
wagtail_photo_gallery/static/photo_gallery_admin.js
wagtail_photo_gallery/static/wagtail_photo_gallery/css/album-image-panel.css
wagtail_photo_gallery/static/wagtail_photo_gallery/css/photo-gallery.css
wagtail_photo_gallery/static/wagtail_photo_gallery/css/select-and-sort.css
wagtail_photo_gallery-0.2.0.dist-info/LICENSE
wagtail_photo_gallery-0.2.0.dist-info/METADATA
wagtail_photo_gallery-0.2.0.dist-info/WHEEL
wagtail_photo_gallery-0.2.0.dist-info/top_level.txt
wagtail_photo_gallery-0.2.0.dist-info/RECORD
