Metadata-Version: 2.1
Name: wagtail-photo-gallery
Version: 0.2.0
Summary: An image gallery plugin for Wagtail
Home-page: https://github.com/donhauser/wagtail-photo-gallery
Author: Jonas Donhauser
Classifier: Development Status :: 4 - Beta
Classifier: Programming Language :: Python :: 3
Classifier: Programming Language :: Python :: 3.8
Classifier: Programming Language :: Python :: 3.9
Classifier: Programming Language :: Python :: 3.10
Classifier: Programming Language :: Python :: 3.11
Classifier: Programming Language :: Python :: 3.12
Classifier: Framework :: Django
Classifier: Framework :: Django :: 4.2
Classifier: Framework :: Django :: 5.0
Classifier: Framework :: Django :: 5.1
Classifier: Framework :: Wagtail
Classifier: Framework :: Wagtail :: 6
Classifier: Intended Audience :: Developers
Classifier: License :: OSI Approved :: Apache Software License
Classifier: Programming Language :: Python :: 3
Classifier: Topic :: Internet :: WWW/HTTP :: Site Management
Classifier: Topic :: Software Development :: Libraries :: Python Modules
Requires-Python: >=3.8
License-File: LICENSE
Requires-Dist: wagtail>=6.0.2
Requires-Dist: django-imagekit
Provides-Extra: pillow
Requires-Dist: pillow; extra == "pillow"
Provides-Extra: pillow-simd
Requires-Dist: pillow-simd; extra == "pillow-simd"
